{
	"langid":              "LANG_GERMAN",
	"sublangid":           "SUBLANG_GERMAN",
	"strings": {
		"FILENAME":            "Name",
		"ALGORITHM":           "Algorithmus",
		"COPIED":              "✔ Kopiert",
		"HASH":                "Hash",
		"CHECK_AGAINST":       "Vergleichen mit:",
		"EXPORT_TO":           "Exportieren als Prüfsummendatei:",
		"EXPORT_BTN":          "Exportieren...",
		"SUMFILE":             "Als Prüfsummendatei interpretiert.",
		"DONE":                "Fertig!",
		"PROCESSING":          "In Bearbeitung...",
		"HASHES":              "Hashwerte",
		"CLIPBOARD":           "In Zwischenablage",
		"NOMATCH":             "Keine Übereinstimmung gefunden.",
		"ERROR":               "Fehler"
	}
}
