{
    "langid": "",
    "sublangid": "",
    "strings": {
        "FILENAME": "Nome",
        "ALGORITHM": "Algoritmo",
        "COPIED": "✔ Copiado",
        "HASH": "Hash",
        "CHECK_AGAINST": "Cotexar con:",
        "EXPORT_TO": "Exportar a ficheiro suma:",
        "EXPORT_BTN": "Exportar…",
        "SUMFILE": "Interpretado como ficheiro suma.",
        "DONE": "Feito!",
        "PROCESSING": "Procesando…",
        "HASHES": "Hashes",
        "CLIPBOARD": "Ao portapapeis",
        "NOMATCH": "Non se atoparon coincidencias.",
        "ERROR": "Erro",
        "CANCEL": "Cancelar",
        "DISPLAY_UPPERCASE": "Mostrar hashes en maiúscula",
        "LOOK_FOR_SUMFILES": "Buscar ficheiros suma xunto aos ficheiros que se están a analizar",
        "SUMFILE_UPPERCASE": "Exportar hashes en maiúscula",
        "SUMFILE_UNIX_ENDINGS": "Exportar ficheiros con final de liña Unix (LF)",
        "SUMFILE_USE_DOUBLE_SPACE": "",
        "SUMFILE_FORWARD_SLASHES": "",
        "SUMFILE_DOT_HASH_COMPATIBLE": "",
        "SUMFILE_BANNER": "",
        "SUMFILE_BANNER_DATE": "",
        "CHECK_FOR_UPDATES": "",
        "COPY_HASH": "",
        "COPY_LINE": "",
        "COPY_FILE": "",
        "COPY_EVERYTHING": "",
        "VT_NO_COMPATIBLE": "",
        "VT_NOT_FOUND": "",
        "UPDATE_DISABLED_IN_DEV_BUILD": "",
        "UPDATE_AVAILABLE_TITLE": "",
        "UPDATE_AVAILABLE_TEXT": "",
        "UPDATE_NEWEST_TITLE": "",
        "UPDATE_NEWEST_TEXT": "",
        "CLIPBOARD_AUTOENABLE": "",
        "CLIPBOARD_AUTOENABLE_IF_NONE": "",
        "CLIPBOARD_AUTOENABLE_EXCLUSIVE": "",
        "SETTINGS_TITLE": "",
        "CHECKAGAINST_AUTOFORMAT": "",
        "CHECKAGAINST_STRICT": "",
        "HASH_SUMFILE_TOO": "",
        "ITEM_MATCHING": "",
        "ITEMS_MATCHING": "",
        "SUMFILE_ALGORITHM_ONLY": "",
        "ERROR_GROUP": "",
        "MATCH_GROUP": "",
        "MISMATCH_GROUP": "",
        "INSECURE_GROUP": "",
        "UNKNOWN_GROUP": "",
        "FOREGROUND": "",
        "BACKGROUND": ""
    }
}
