{
    "langid": "LANG_PORTUGUESE",
    "sublangid": "SUBLANG_PORTUGUESE",
    "strings": {
        "FILENAME": "Nome",
        "ALGORITHM": "Algoritmo",
        "COPIED": "✔ Copiado",
        "HASH": "Hash",
        "CHECK_AGAINST": "Verificar contra:",
        "EXPORT_TO": "Exportar para ficheiro de soma:",
        "EXPORT_BTN": "Exportar…",
        "SUMFILE": "Interpretado como ficheiro de soma.",
        "DONE": "Concluído!",
        "PROCESSING": "A processar…",
        "HASHES": "Hashes",
        "CLIPBOARD": "Para a área de transferência",
        "NOMATCH": "Nenhuma correspondência encontrada.",
        "ERROR": "Erro",
        "CANCEL": "Cancelar",
        "DISPLAY_UPPERCASE": "Exibir hashes em letras maiúsculas",
        "LOOK_FOR_SUMFILES": "Procurar ficheiros de soma próximos aos ficheiros que estão sendo “hasheados”",
        "SUMFILE_UPPERCASE": "Exportar hashes em letras maiúsculas",
        "SUMFILE_UNIX_ENDINGS": "Exportar ficheiros com finais de linha Unix",
        "SUMFILE_USE_DOUBLE_SPACE": "Exportar ficheiros de soma com espaço duplo em vez de espaço-asterisco",
        "SUMFILE_FORWARD_SLASHES": "Usar caminhos com barras nos ficheiros exportados",
        "SUMFILE_DOT_HASH_COMPATIBLE": "Exportar ficheiros de soma em formato compatível com o .hash do corz",
        "SUMFILE_BANNER": "Adicionar banner aos ficheiros exportados",
        "SUMFILE_BANNER_DATE": "Adicionar data ao banner",
        "CHECK_FOR_UPDATES": "Verificar atualizações",
        "COPY_HASH": "Copiar hash",
        "COPY_LINE": "Copiar linha",
        "COPY_FILE": "Copiar nome do ficheiro",
        "COPY_EVERYTHING": "Copiar tudo",
        "VT_NO_COMPATIBLE": "Nenhum algoritmo compatível ativado",
        "VT_NOT_FOUND": "Não encontrado no banco de dados",
        "UPDATE_DISABLED_IN_DEV_BUILD": "Indisponível em versões de desenvolvimento",
        "UPDATE_AVAILABLE_TITLE": "Atualização disponível",
        "UPDATE_AVAILABLE_TEXT": "Nova versão %hu.%hu.%hu disponível",
        "UPDATE_NEWEST_TITLE": "Parabéns",
        "UPDATE_NEWEST_TEXT": "Já está na versão mais recente",
        "CLIPBOARD_AUTOENABLE": "Se a área de transferência contiver um hash, ative automaticamente algoritmos do mesmo comprimento para a execução",
        "CLIPBOARD_AUTOENABLE_IF_NONE": "Somente se nenhum algoritmo do mesmo comprimento estiver ativado",
        "CLIPBOARD_AUTOENABLE_EXCLUSIVE": "Desativar todos os outros algoritmos",
        "SETTINGS_TITLE": "Configurações",
        "CHECKAGAINST_AUTOFORMAT": "Reformatar automaticamente hashes colados no campo de verificação",
        "CHECKAGAINST_STRICT": "Modo rigoroso para o campo de verificação de hash",
        "HASH_SUMFILE_TOO": "Ao processar um ficheiro de soma, calcule o hash do ficheiro de soma também",
        "ITEM_MATCHING": "1 ficheiro correspondente",
        "ITEMS_MATCHING": "%d ficheiros correspondentes",
        "SUMFILE_ALGORITHM_ONLY": "Ao processar um ficheiro de soma de algoritmo conhecido, desative outros algoritmos",
        "ERROR_GROUP": "Erro",
        "MATCH_GROUP": "Correspondência",
        "MISMATCH_GROUP": "Sem correspondência",
        "INSECURE_GROUP": "Inseguro",
        "UNKNOWN_GROUP": "Desconhecido",
        "FOREGROUND": "Primeiro plano",
        "BACKGROUND": "Segundo plano",
        "SUMMARY": "Resumo",
        "DISPLAY_MONOSPACE": "Exibir hashes em fonte monoespaçada"
    }
}
